screen_assembly/__init__.py
screen_assembly/results/__init__.py
screen_assembly/results/results.py
screen_assembly/run/__init__.py
screen_assembly/run/analysis.py
screen_assembly-1.2.8.data/scripts/screen_assembly3.py
screen_assembly-1.2.8.dist-info/LICENSE
screen_assembly-1.2.8.dist-info/METADATA
screen_assembly-1.2.8.dist-info/WHEEL
screen_assembly-1.2.8.dist-info/top_level.txt
screen_assembly-1.2.8.dist-info/RECORD
