Metadata-Version: 2.1
Name: screen-assembly
Version: 1.2.8
Summary: screens for presence of genes of interest (GOI) in bacterial assemblies
Home-page: https://github.com/shimbalama/screen_assembly.git
Author: Liam McIntyre
Author-email: shimbalama@gmail.com
License: MIT
Keywords: screen assemblies bacteria gene
Platform: UNKNOWN
Classifier: Programming Language :: Python :: 3
Classifier: License :: OSI Approved :: MIT License
Classifier: Operating System :: OS Independent
License-File: LICENSE
Requires-Dist: pandas
Requires-Dist: biopython
Requires-Dist: matplotlib
